{
	"info": {
		"_postman_id": "14bd63d1-5686-459d-a70f-262dda675874",
		"name": "exercicios-M1S9",
		"schema": "https://schema.getpostman.com/json/collection/v2.1.0/collection.json",
		"_exporter_id": "33961025"
	},
	"item": [
		{
			"name": "Livro",
			"item": [
				{
					"name": "livro",
					"request": {
						"method": "GET",
						"header": [],
						"url": {
							"raw": "{{baseUrl}}/livro",
							"host": [
								"{{baseUrl}}"
							],
							"path": [
								"livro"
							]
						}
					},
					"response": []
				},
				{
					"name": "livro",
					"request": {
						"method": "POST",
						"header": [],
						"body": {
							"mode": "raw",
							"raw": "{\n    \"titulo\": \"Front-end 3\",\n    \"autor\": \"Pessoa importante\",\n    \"anoPublicacao\": \"1090\"\n}",
							"options": {
								"raw": {
									"language": "json"
								}
							}
						},
						"url": {
							"raw": "{{baseUrl}}/livro",
							"host": [
								"{{baseUrl}}"
							],
							"path": [
								"livro"
							]
						}
					},
					"response": []
				},
				{
					"name": "livro",
					"request": {
						"method": "PUT",
						"header": [],
						"body": {
							"mode": "raw",
							"raw": "{\n    \"id\": 4,\n    \"titulo\": \"livro teste \",\n    \"autor\": \"Cheryl \",\n    \"anoPublicacao\": \"2024\"\n}",
							"options": {
								"raw": {
									"language": "json"
								}
							}
						},
						"url": {
							"raw": "{{baseUrl}}/livro",
							"host": [
								"{{baseUrl}}"
							],
							"path": [
								"livro"
							]
						}
					},
					"response": []
				},
				{
					"name": "livro",
					"request": {
						"method": "DELETE",
						"header": [],
						"body": {
							"mode": "raw",
							"raw": "",
							"options": {
								"raw": {
									"language": "json"
								}
							}
						},
						"url": {
							"raw": "{{baseUrl}}/livro?id=4",
							"host": [
								"{{baseUrl}}"
							],
							"path": [
								"livro"
							],
							"query": [
								{
									"key": "id",
									"value": "4"
								}
							]
						}
					},
					"response": []
				}
			]
		},
		{
			"name": "Membro",
			"item": [
				{
					"name": "membro",
					"request": {
						"method": "GET",
						"header": [],
						"url": {
							"raw": "{{baseUrl}}/membro",
							"host": [
								"{{baseUrl}}"
							],
							"path": [
								"membro"
							]
						}
					},
					"response": []
				},
				{
					"name": "membro",
					"request": {
						"method": "POST",
						"header": [],
						"body": {
							"mode": "raw",
							"raw": "{\n    \"nome\": \"Bianca de Mello\",\n    \"endereco\": \"Rua das Flores\",\n    \"telefone\": \"47 12345678\"\n}",
							"options": {
								"raw": {
									"language": "json"
								}
							}
						},
						"url": {
							"raw": "{{baseUrl}}/membro",
							"host": [
								"{{baseUrl}}"
							],
							"path": [
								"membro"
							]
						}
					},
					"response": []
				},
				{
					"name": "membro",
					"request": {
						"method": "PUT",
						"header": [],
						"body": {
							"mode": "raw",
							"raw": "{\n    \"id\": 3,\n    \"nome\": \"Maria de Lourdes \",\n    \"endereco\": \"Avenida Paulista \",\n    \"telefone\": \"48 11111111\"\n}",
							"options": {
								"raw": {
									"language": "json"
								}
							}
						},
						"url": {
							"raw": "{{baseUrl}}/membro",
							"host": [
								"{{baseUrl}}"
							],
							"path": [
								"membro"
							]
						}
					},
					"response": []
				},
				{
					"name": "membro",
					"event": [
						{
							"listen": "test",
							"script": {
								"exec": [
									""
								],
								"type": "text/javascript",
								"packages": {}
							}
						}
					],
					"request": {
						"method": "DELETE",
						"header": [],
						"body": {
							"mode": "raw",
							"raw": "",
							"options": {
								"raw": {
									"language": "json"
								}
							}
						},
						"url": {
							"raw": "{{baseUrl}}/membro?id=3",
							"host": [
								"{{baseUrl}}"
							],
							"path": [
								"membro"
							],
							"query": [
								{
									"key": "id",
									"value": "3"
								}
							]
						}
					},
					"response": []
				}
			]
		},
		{
			"name": "Emprestimos",
			"item": [
				{
					"name": "emprestimos",
					"request": {
						"method": "GET",
						"header": [],
						"url": {
							"raw": "{{baseUrl}}/emprestimos",
							"host": [
								"{{baseUrl}}"
							],
							"path": [
								"emprestimos"
							],
							"query": [
								{
									"key": "",
									"value": "",
									"disabled": true
								}
							]
						}
					},
					"response": []
				},
				{
					"name": "emprestimos",
					"request": {
						"method": "POST",
						"header": [],
						"body": {
							"mode": "raw",
							"raw": "{\n    \"livro\":{\n        \"id\": 1\n    },\n        \"membro\":{\n        \"id\": 1\n    },\n    \"dataEmprestimo\": \"1990-02-02\",\n    \"dataDevolucao\": \"1990-02-02\"\n}",
							"options": {
								"raw": {
									"language": "json"
								}
							}
						},
						"url": {
							"raw": "{{baseUrl}}/emprestimos",
							"host": [
								"{{baseUrl}}"
							],
							"path": [
								"emprestimos"
							]
						}
					},
					"response": []
				},
				{
					"name": "emprestimos",
					"request": {
						"method": "PUT",
						"header": [],
						"body": {
							"mode": "raw",
							"raw": "{\n    \"id\": 4,\n    \"livro\":{\n        \"id\": 1\n    },\n        \"membro\":{\n        \"id\": 2\n    },\n    \"dataEmprestimo\": \"1990-02-04\",\n    \"dataDevolucao\": \"1990-02-05\"\n}",
							"options": {
								"raw": {
									"language": "json"
								}
							}
						},
						"url": {
							"raw": "{{baseUrl}}/emprestimos",
							"host": [
								"{{baseUrl}}"
							],
							"path": [
								"emprestimos"
							]
						}
					},
					"response": []
				},
				{
					"name": "emprestimos",
					"event": [
						{
							"listen": "test",
							"script": {
								"exec": [
									""
								],
								"type": "text/javascript",
								"packages": {}
							}
						}
					],
					"request": {
						"method": "DELETE",
						"header": [],
						"body": {
							"mode": "raw",
							"raw": "",
							"options": {
								"raw": {
									"language": "json"
								}
							}
						},
						"url": {
							"raw": "{{baseUrl}}/emprestimos?id=4",
							"host": [
								"{{baseUrl}}"
							],
							"path": [
								"emprestimos"
							],
							"query": [
								{
									"key": "id",
									"value": "4"
								}
							]
						}
					},
					"response": []
				}
			]
		},
		{
			"name": "Bibliotecario",
			"item": [
				{
					"name": "bibliotecario",
					"request": {
						"method": "GET",
						"header": [],
						"url": {
							"raw": "{{baseUrl}}/bibliotecario",
							"host": [
								"{{baseUrl}}"
							],
							"path": [
								"bibliotecario"
							]
						}
					},
					"response": []
				},
				{
					"name": "bibliotecario",
					"request": {
						"method": "POST",
						"header": [],
						"body": {
							"mode": "raw",
							"raw": "{\n    \"nome\": \"Carlos Alberto\",\n    \"email\": \"carlosalberto@gmail.com\",\n    \"senha\": \"password55\"\n}",
							"options": {
								"raw": {
									"language": "json"
								}
							}
						},
						"url": {
							"raw": "{{baseUrl}}/bibliotecario",
							"host": [
								"{{baseUrl}}"
							],
							"path": [
								"bibliotecario"
							]
						}
					},
					"response": []
				},
				{
					"name": "bibliotecario",
					"request": {
						"method": "PUT",
						"header": [],
						"body": {
							"mode": "raw",
							"raw": "{\n    \"id\": 4,\n    \"nome\": \"Carlos Alberto Ferreira\",\n    \"email\": \"carlosalberto@gmail.com\",\n    \"senha\": \"password55\"\n}",
							"options": {
								"raw": {
									"language": "json"
								}
							}
						},
						"url": {
							"raw": "{{baseUrl}}/bibliotecario",
							"host": [
								"{{baseUrl}}"
							],
							"path": [
								"bibliotecario"
							]
						}
					},
					"response": []
				},
				{
					"name": "bibliotecario",
					"event": [
						{
							"listen": "test",
							"script": {
								"exec": [
									""
								],
								"type": "text/javascript",
								"packages": {}
							}
						}
					],
					"request": {
						"method": "DELETE",
						"header": [],
						"body": {
							"mode": "raw",
							"raw": "",
							"options": {
								"raw": {
									"language": "json"
								}
							}
						},
						"url": {
							"raw": "{{baseUrl}}/bibliotecario?id=3",
							"host": [
								"{{baseUrl}}"
							],
							"path": [
								"bibliotecario"
							],
							"query": [
								{
									"key": "id",
									"value": "3"
								}
							]
						}
					},
					"response": []
				}
			]
		},
		{
			"name": "Visitante",
			"item": [
				{
					"name": "visitante",
					"request": {
						"method": "GET",
						"header": [],
						"url": {
							"raw": "{{baseUrl}}/visitante",
							"host": [
								"{{baseUrl}}"
							],
							"path": [
								"visitante"
							]
						}
					},
					"response": []
				},
				{
					"name": "visitante",
					"request": {
						"method": "POST",
						"header": [],
						"body": {
							"mode": "raw",
							"raw": "{\n    \"nome\": \"Albert Eistein\",\n    \"telefone\": \"47 12345678\"\n}",
							"options": {
								"raw": {
									"language": "json"
								}
							}
						},
						"url": {
							"raw": "{{baseUrl}}/visitante",
							"host": [
								"{{baseUrl}}"
							],
							"path": [
								"visitante"
							]
						}
					},
					"response": []
				},
				{
					"name": "visitante",
					"request": {
						"method": "PUT",
						"header": [],
						"body": {
							"mode": "raw",
							"raw": "{\n    \"id\": 3,\n    \"nome\": \"Maria de Lourdes \",\n    \"telefone\": \"48 11111111\"\n}",
							"options": {
								"raw": {
									"language": "json"
								}
							}
						},
						"url": {
							"raw": "{{baseUrl}}/visitante",
							"host": [
								"{{baseUrl}}"
							],
							"path": [
								"visitante"
							]
						}
					},
					"response": []
				},
				{
					"name": "visitante",
					"event": [
						{
							"listen": "test",
							"script": {
								"exec": [
									""
								],
								"type": "text/javascript",
								"packages": {}
							}
						}
					],
					"request": {
						"method": "DELETE",
						"header": [],
						"body": {
							"mode": "raw",
							"raw": "",
							"options": {
								"raw": {
									"language": "json"
								}
							}
						},
						"url": {
							"raw": "{{baseUrl}}/visitante?id=3",
							"host": [
								"{{baseUrl}}"
							],
							"path": [
								"visitante"
							],
							"query": [
								{
									"key": "id",
									"value": "3"
								}
							]
						}
					},
					"response": []
				}
			]
		}
	],
	"variable": [
		{
			"key": "baseUrl",
			"value": "localhost:8080"
		}
	]
}